mobpush/DeviceV3Client.py
mobpush/PushV3Client.py
mobpush/PushWorkBuilder.py
mobpush/SendRequest.py
mobpush/StatsV3Client.py
mobpush/__init__.py
mobpush/model/BasePush.py
mobpush/model/Push.py
mobpush/model/PushForward.py
mobpush/model/PushMulti.py
mobpush/model/PushNotify.py
mobpush/model/PushOperator.py
mobpush/model/PushTarget.py
mobpush/model/__init__.py
mobPushSdkV3-2.0.0.dist-info/LICENCE
mobPushSdkV3-2.0.0.dist-info/METADATA
mobPushSdkV3-2.0.0.dist-info/WHEEL
mobPushSdkV3-2.0.0.dist-info/top_level.txt
mobPushSdkV3-2.0.0.dist-info/zip-safe
mobPushSdkV3-2.0.0.dist-info/RECORD
